[
  {
    "date": "2024-12-31",
    "symbol": "GOOG",
    "reportedCurrency": "USD",
    "cik": "0001652044",
    "fillingDate": "2025-02-05",
    "acceptedDate": "2025-02-04 20:41:40",
    "calendarYear": "2024",
    "period": "FY",
    "cashAndCashEquivalents": 23466000000,
    "shortTermInvestments": 72191000000,
    "cashAndShortTermInvestments": 95657000000,
    "netReceivables": 52340000000,
    "inventory": 0,
    "otherCurrentAssets": 15714000000,
    "totalCurrentAssets": 163711000000,
    "propertyPlantEquipmentNet": 184624000000,
    "goodwill": 31885000000,
    "intangibleAssets": 0,
    "goodwillAndIntangibleAssets": 31885000000,
    "longTermInvestments": 37982000000,
    "taxAssets": 17180000000,
    "otherNonCurrentAssets": 14874000000,
    "totalNonCurrentAssets": 286545000000,
    "otherAssets": 0,
    "totalAssets": 450256000000,
    "accountPayables": 7987000000,
    "shortTermDebt": 2887000000,
    "taxPayables": 8782000000,
    "deferredRevenue": 5036000000,
    "otherCurrentLiabilities": 64430000000,
    "totalCurrentLiabilities": 89122000000,
    "longTermDebt": 22574000000,
    "deferredRevenueNonCurrent": 0,
    "deferredTaxLiabilitiesNonCurrent": 0,
    "otherNonCurrentLiabilities": 13476000000,
    "totalNonCurrentLiabilities": 36050000000,
    "otherLiabilities": 0,
    "capitalLeaseObligations": 14578000000,
    "totalLiabilities": 125172000000,
    "preferredStock": 0,
    "commonStock": 84800000000,
    "retainedEarnings": 245084000000,
    "accumulatedOtherComprehensiveIncomeLoss": -4800000000,
    "othertotalStockholdersEquity": 0,
    "totalStockholdersEquity": 325084000000,
    "totalEquity": 325084000000,
    "totalLiabilitiesAndStockholdersEquity": 450256000000,
    "minorityInterest": 0,
    "totalLiabilitiesAndTotalEquity": 450256000000,
    "totalInvestments": 110173000000,
    "totalDebt": 25461000000,
    "netDebt": 1995000000,
    "link": "https://www.sec.gov/Archives/edgar/data/1652044/000165204425000014/0001652044-25-000014-index.htm",
    "finalLink": "https://www.sec.gov/Archives/edgar/data/1652044/000165204425000014/goog-20241231.htm"
  },
  {
    "date": "2023-12-31",
    "symbol": "GOOG",
    "reportedCurrency": "USD",
    "cik": "0001652044",
    "fillingDate": "2024-01-31",
    "acceptedDate": "2024-01-30 21:43:43",
    "calendarYear": "2023",
    "period": "FY",
    "cashAndCashEquivalents": 24048000000,
    "shortTermInvestments": 86868000000,
    "cashAndShortTermInvestments": 110916000000,
    "netReceivables": 47964000000,
    "inventory": 0,
    "otherCurrentAssets": 12650000000,
    "totalCurrentAssets": 171530000000,
    "propertyPlantEquipmentNet": 148436000000,
    "goodwill": 29198000000,
    "intangibleAssets": 0,
    "goodwillAndIntangibleAssets": 29198000000,
    "longTermInvestments": 31008000000,
    "taxAssets": 12169000000,
    "otherNonCurrentAssets": 10051000000,
    "totalNonCurrentAssets": 230862000000,
    "otherAssets": 0,
    "totalAssets": 402392000000,
    "accountPayables": 7493000000,
    "shortTermDebt": 2791000000,
    "taxPayables": 2748000000,
    "deferredRevenue": 4137000000,
    "otherCurrentLiabilities": 64645000000,
    "totalCurrentLiabilities": 81814000000,
    "longTermDebt": 25350000000,
    "deferredRevenueNonCurrent": 911000000,
    "deferredTaxLiabilitiesNonCurrent": 485000000,
    "otherNonCurrentLiabilities": 10453000000,
    "totalNonCurrentLiabilities": 37199000000,
    "otherLiabilities": 0,
    "capitalLeaseObligations": 16634000000,
    "totalLiabilities": 119013000000,
    "preferredStock": 0,
    "commonStock": 76534000000,
    "retainedEarnings": 211247000000,
    "accumulatedOtherComprehensiveIncomeLoss": -4402000000,
    "othertotalStockholdersEquity": 0,
    "totalStockholdersEquity": 283379000000,
    "totalEquity": 283379000000,
    "totalLiabilitiesAndStockholdersEquity": 402392000000,
    "minorityInterest": 0,
    "totalLiabilitiesAndTotalEquity": 402392000000,
    "totalInvestments": 117876000000,
    "totalDebt": 27121000000,
    "netDebt": 3073000000,
    "link": "https://www.sec.gov/Archives/edgar/data/1652044/000165204424000022/0001652044-24-000022-index.htm",
    "finalLink": "https://www.sec.gov/Archives/edgar/data/1652044/000165204424000022/goog-20231231.htm"
  },
  {
    "date": "2022-12-31",
    "symbol": "GOOG",
    "reportedCurrency": "USD",
    "cik": "0001652044",
    "fillingDate": "2023-02-03",
    "acceptedDate": "2023-02-02 21:23:45",
    "calendarYear": "2022",
    "period": "FY",
    "cashAndCashEquivalents": 21879000000,
    "shortTermInvestments": 91883000000,
    "cashAndShortTermInvestments": 113762000000,
    "netReceivables": 40258000000,
    "inventory": 2670000000,
    "otherCurrentAssets": 8105000000,
    "totalCurrentAssets": 164795000000,
    "propertyPlantEquipmentNet": 127049000000,
    "goodwill": 28960000000,
    "intangibleAssets": 2084000000,
    "goodwillAndIntangibleAssets": 31044000000,
    "longTermInvestments": 30492000000,
    "taxAssets": 5261000000,
    "otherNonCurrentAssets": 6623000000,
    "totalNonCurrentAssets": 200469000000,
    "otherAssets": 0,
    "totalAssets": 365264000000,
    "accountPayables": 5128000000,
    "shortTermDebt": 2477000000,
    "taxPayables": 9258000000,
    "deferredRevenue": 3908000000,
    "otherCurrentLiabilities": 48529000000,
    "totalCurrentLiabilities": 69300000000,
    "longTermDebt": 39703000000,
    "deferredRevenueNonCurrent": 599000000,
    "deferredTaxLiabilitiesNonCurrent": 514000000,
    "otherNonCurrentLiabilities": -996000000,
    "totalNonCurrentLiabilities": 39820000000,
    "otherLiabilities": 0,
    "capitalLeaseObligations": 14978000000,
    "totalLiabilities": 109120000000,
    "preferredStock": 0,
    "commonStock": 68184000000,
    "retainedEarnings": 195563000000,
    "accumulatedOtherComprehensiveIncomeLoss": -7603000000,
    "othertotalStockholdersEquity": 0,
    "totalStockholdersEquity": 256144000000,
    "totalEquity": 256144000000,
    "totalLiabilitiesAndStockholdersEquity": 365264000000,
    "minorityInterest": 0,
    "totalLiabilitiesAndTotalEquity": 365264000000,
    "totalInvestments": 122375000000,
    "totalDebt": 29679000000,
    "netDebt": 7800000000,
    "link": "https://www.sec.gov/Archives/edgar/data/1652044/000165204423000016/0001652044-23-000016-index.htm",
    "finalLink": "https://www.sec.gov/Archives/edgar/data/1652044/000165204423000016/goog-20221231.htm"
  },
  {
    "date": "2021-12-31",
    "symbol": "GOOG",
    "reportedCurrency": "USD",
    "cik": "0001652044",
    "fillingDate": "2022-02-02",
    "acceptedDate": "2022-02-01 21:08:02",
    "calendarYear": "2021",
    "period": "FY",
    "cashAndCashEquivalents": 20945000000,
    "shortTermInvestments": 118704000000,
    "cashAndShortTermInvestments": 139649000000,
    "netReceivables": 39304000000,
    "inventory": 1170000000,
    "otherCurrentAssets": 8020000000,
    "totalCurrentAssets": 188143000000,
    "propertyPlantEquipmentNet": 110558000000,
    "goodwill": 22956000000,
    "intangibleAssets": 1417000000,
    "goodwillAndIntangibleAssets": 24373000000,
    "longTermInvestments": 29549000000,
    "taxAssets": 1284000000,
    "otherNonCurrentAssets": 5361000000,
    "totalNonCurrentAssets": 171125000000,
    "otherAssets": 0,
    "totalAssets": 359268000000,
    "accountPayables": 6037000000,
    "shortTermDebt": 2189000000,
    "taxPayables": 808000000,
    "deferredRevenue": 3288000000,
    "otherCurrentLiabilities": 51932000000,
    "totalCurrentLiabilities": 64254000000,
    "longTermDebt": 39568000000,
    "deferredRevenueNonCurrent": 535000000,
    "deferredTaxLiabilitiesNonCurrent": 5257000000,
    "otherNonCurrentLiabilities": -1981000000,
    "totalNonCurrentLiabilities": 43379000000,
    "otherLiabilities": 0,
    "capitalLeaseObligations": 15551000000,
    "totalLiabilities": 107633000000,
    "preferredStock": 0,
    "commonStock": 61774000000,
    "retainedEarnings": 191484000000,
    "accumulatedOtherComprehensiveIncomeLoss": -1623000000,
    "othertotalStockholdersEquity": 0,
    "totalStockholdersEquity": 251635000000,
    "totalEquity": 251635000000,
    "totalLiabilitiesAndStockholdersEquity": 359268000000,
    "minorityInterest": 0,
    "totalLiabilitiesAndTotalEquity": 359268000000,
    "totalInvestments": 148253000000,
    "totalDebt": 26206000000,
    "netDebt": 5261000000,
    "link": "https://www.sec.gov/Archives/edgar/data/1652044/000165204422000019/0001652044-22-000019-index.htm",
    "finalLink": "https://www.sec.gov/Archives/edgar/data/1652044/000165204422000019/goog-20211231.htm"
  },
  {
    "date": "2020-12-31",
    "symbol": "GOOG",
    "reportedCurrency": "USD",
    "cik": "0001652044",
    "fillingDate": "2021-02-03",
    "acceptedDate": "2021-02-02 20:12:25",
    "calendarYear": "2020",
    "period": "FY",
    "cashAndCashEquivalents": 26465000000,
    "shortTermInvestments": 110229000000,
    "cashAndShortTermInvestments": 136694000000,
    "netReceivables": 31384000000,
    "inventory": 728000000,
    "otherCurrentAssets": 5490000000,
    "totalCurrentAssets": 174296000000,
    "propertyPlantEquipmentNet": 96960000000,
    "goodwill": 21175000000,
    "intangibleAssets": 1445000000,
    "goodwillAndIntangibleAssets": 22620000000,
    "longTermInvestments": 20703000000,
    "taxAssets": 1084000000,
    "otherNonCurrentAssets": 3953000000,
    "totalNonCurrentAssets": 145320000000,
    "otherAssets": 0,
    "totalAssets": 319616000000,
    "accountPayables": 5589000000,
    "shortTermDebt": 1694000000,
    "taxPayables": 1485000000,
    "deferredRevenue": 2543000000,
    "otherCurrentLiabilities": 45523000000,
    "totalCurrentLiabilities": 56834000000,
    "longTermDebt": 37324000000,
    "deferredRevenueNonCurrent": 481000000,
    "deferredTaxLiabilitiesNonCurrent": 3561000000,
    "otherNonCurrentLiabilities": -1128000000,
    "totalNonCurrentLiabilities": 40238000000,
    "otherLiabilities": 0,
    "capitalLeaseObligations": 13940000000,
    "totalLiabilities": 97072000000,
    "preferredStock": 0,
    "commonStock": 58510000000,
    "retainedEarnings": 163401000000,
    "accumulatedOtherComprehensiveIncomeLoss": 633000000,
    "othertotalStockholdersEquity": 0,
    "totalStockholdersEquity": 222544000000,
    "totalEquity": 222544000000,
    "totalLiabilitiesAndStockholdersEquity": 319616000000,
    "minorityInterest": 0,
    "totalLiabilitiesAndTotalEquity": 319616000000,
    "totalInvestments": 130932000000,
    "totalDebt": 25078000000,
    "netDebt": -1387000000,
    "link": "https://www.sec.gov/Archives/edgar/data/1652044/000165204421000010/0001652044-21-000010-index.htm",
    "finalLink": "https://www.sec.gov/Archives/edgar/data/1652044/000165204421000010/goog-20201231.htm"
  }
]